{"group": {"group": "042_remotevpn", "action": {"do": 1, "status": 1}}, "rules": [{"PK": "client-teamviewer-com.trafficmanager.net", "action": {"do": 1, "status": 1}}, {"PK": "teamviewer.com.cdn.cloudflare.net", "action": {"do": 1, "status": 1}}, {"PK": "anydesk.com", "action": {"do": 1, "status": 1}}, {"PK": "cftunnel.com", "action": {"do": 1, "status": 1}}, {"PK": "cloudflareaccess.com", "action": {"do": 1, "status": 1}}, {"PK": "cloudflareresearch.com", "action": {"do": 1, "status": 1}}, {"PK": "h2.cftunnel.com", "action": {"do": 1, "status": 1}}, {"PK": "net.anydesk.com", "action": {"do": 1, "status": 1}}, {"PK": "quic.cftunnel.com", "action": {"do": 1, "status": 1}}, {"PK": "tailscale.com", "action": {"do": 1, "status": 1}}, {"PK": "tailscale.io", "action": {"do": 1, "status": 1}}, {"PK": "teamviewer.cn", "action": {"do": 1, "status": 1}}, {"PK": "teamviewer.com", "action": {"do": 1, "status": 1}}, {"PK": "teamviewer.us", "action": {"do": 1, "status": 1}}, {"PK": "ts.net", "action": {"do": 1, "status": 1}}, {"PK": "update.argotunnel.com", "action": {"do": 1, "status": 1}}, {"PK": "zerotier.com", "action": {"do": 1, "status": 1}}]}